WishartMoments/Expectations.py
WishartMoments/Jacks.py
WishartMoments/ObjectWithPartitions.py
WishartMoments/__init__.py
WishartMoments-0.0.3.dist-info/LICENSE.py
WishartMoments-0.0.3.dist-info/METADATA
WishartMoments-0.0.3.dist-info/WHEEL
WishartMoments-0.0.3.dist-info/top_level.txt
WishartMoments-0.0.3.dist-info/RECORD
