Metadata-Version: 2.1
Name: WishartMoments
Version: 0.0.3
Summary: A package to compute all the invariant Wishart moments.
Home-page: http://github.com/antunescarles/wishart-moments-calculator
Author: Carlos Antunes Percincula
Author-email: antunes.p.carlos@hotmail.com
License: UNKNOWN
Project-URL: Bug Tracker, https://github.com/pypa/sampleproject/issues
Platform: UNKNOWN
Classifier: Programming Language :: Python :: 3
Classifier: License :: OSI Approved :: MIT License
Classifier: Operating System :: OS Independent
Requires-Python: >=3.6
License-File: LICENSE.py
